btpy/__init__.py
btpy/application.py
btpy/az.py
btpy/commands/ad_commands.py
btpy/commands/config_commands.py
btpy/commands/env_commands.py
btpy/commands/iac_commands.py
btpy/commands/migration_commands.py
btpy/commands/software_commands.py
btpy/commands/tenant_commands.py
btpy/commands/version_commands.py
btpy/configuration/aliases.py
btpy/configuration/config.py
btpy/core/__init__.py
btpy/core/ad.py
btpy/core/azure_utility.py
btpy/core/envs/__init__.py
btpy/core/envs/desc_templates/bt_3_0_0.json
btpy/core/envs/env2.py
btpy/core/envs/env_client.py
btpy/core/envs/env_desc.py
btpy/core/envs/env_desc_loader.py
btpy/core/envs/env_migrator.py
btpy/core/envs/env_utility.py
btpy/core/envs/templates/env-config.yaml.mustache
btpy/core/envs/templates/env-eso.yaml.mustache
btpy/core/envs/templates/env-terraform.tfvars.json.mustache
btpy/core/file_utility.py
btpy/core/iac_utility.py
btpy/core/k8s_utility.py
btpy/core/migrations/__init__.py
btpy/core/migrations/migration_loader.py
btpy/core/migrations/migration_runner.py
btpy/core/misc_utility.py
btpy/core/rancher.py
btpy/core/rancher_utility.py
btpy/core/resource_clients/azure/azure_appservice_client.py
btpy/core/resource_clients/azure/azure_function_client.py
btpy/core/resource_clients/azure/azure_storage_web_client.py
btpy/core/resource_clients/azure/azure_vm_client.py
btpy/core/resource_clients/resource_client.py
btpy/core/resource_clients/resource_client_factory.py
btpy/core/tenant/__init__.py
btpy/core/tenant/templates/flux-tenant.yaml.mustache
btpy/core/tenant/templates/tenant-terraform.tfvars.json.mustache
btpy/core/tenant/tenant.py
btpy/core/versions.py
btpy/cosmosdb.py
btpy/environment.py
btpy/iac/__init__.py
btpy/iac/application.py
btpy/iac/cosmosdb.py
btpy/iac/environment.py
btpy/iac/misc.py
btpy/iac/scripts.py
btpy/iac/stamp.py
btpy/iac/subscription.py
btpy/iac/suffix.py
btpy/iac/templates/backend.mustache
btpy/iac/terraform.py
btpy/iac/tfvars.py
btpy/iac/variables.py
btpy/main.py
btpy/misc.py
beacontower_btpy-0.3.0.dist-info/METADATA
beacontower_btpy-0.3.0.dist-info/WHEEL
beacontower_btpy-0.3.0.dist-info/entry_points.txt
beacontower_btpy-0.3.0.dist-info/RECORD
