Metadata-Version: 2.1
Name: beacontower-btpy
Version: 0.3.0
Summary: 
Author: Fredrik Svensson
Author-email: fredrik@glaze.se
Requires-Python: >=3.11,<4.0
Classifier: Programming Language :: Python :: 3
Classifier: Programming Language :: Python :: 3.11
Classifier: Programming Language :: Python :: 3.12
Requires-Dist: aiohttp (>=3.9.3,<4.0.0)
Requires-Dist: ansible (>=10.2.0,<11.0.0)
Requires-Dist: azure-eventhub (>=5.15.1,<6.0.0)
Requires-Dist: azure-identity (>=1.15.0,<2.0.0)
Requires-Dist: azure-mgmt-appconfiguration (>=3.0.0,<4.0.0)
Requires-Dist: azure-mgmt-compute (>=30.6.0,<31.0.0)
Requires-Dist: azure-mgmt-resource (==24.0.0)
Requires-Dist: azure-mgmt-web (>=7.2.0,<8.0.0)
Requires-Dist: azure-storage-blob (>=12.19.1,<13.0.0)
Requires-Dist: chevron (>=0.14.0,<0.15.0)
Requires-Dist: colorama (>=0.4.6,<0.5.0)
Requires-Dist: cyclopts (>=2.9.4,<3.0.0)
Requires-Dist: dda-python-terraform (>=2.1.1,<3.0.0)
Requires-Dist: gitpython (>=3.1.0,<4.0.0)
Requires-Dist: msgraph-sdk (>=1.49.0,<2.0.0)
Requires-Dist: pyyaml (>=6.0.1,<7.0.0)
Requires-Dist: rich (>=13.7.1,<14.0.0)
Requires-Dist: setuptools (>=75.1.0,<76.0.0)
Requires-Dist: sshkey-tools (>=0.10.3,<0.11.0)
Requires-Dist: typer (>=0.12,<0.13)
